AUTHORS
LICENSE
README.rst
pyproject.toml
setup.cfg
setup.py
bol/__init__.py
bol/openapi/__init__.py
bol/openapi/api.py
bol/plaza/__init__.py
bol/plaza/api.py
bol/plaza/models.py
bol/retailer/__init__.py
bol/retailer/api.py
bol/retailer/constants.py
bol/retailer/models.py
python_bol_api.egg-info/PKG-INFO
python_bol_api.egg-info/SOURCES.txt
python_bol_api.egg-info/dependency_links.txt
python_bol_api.egg-info/not-zip-safe
python_bol_api.egg-info/requires.txt
python_bol_api.egg-info/top_level.txt