Metadata-Version: 1.1
Name: python-bol-api
Version: 0.10.0
Summary: Wrapper for the bol.com API
Home-page: http://www.intenct.info/
Author: Raymond Penners
Author-email: raymond.penners@intenct.nl
License: UNKNOWN
Keywords: bol bol.com api wrapper
Platform: UNKNOWN
Classifier: Development Status :: 4 - Beta
Classifier: Intended Audience :: Developers
Classifier: Intended Audience :: System Administrators
Classifier: Operating System :: OS Independent
Classifier: Topic :: Software Development
Classifier: Topic :: System
Classifier: Topic :: System :: Software Distribution
Classifier: Programming Language :: Python :: 3
Classifier: Programming Language :: Python :: 3.6
Classifier: Programming Language :: Python :: 3.7
Classifier: Programming Language :: Python :: 3.8
Classifier: Programming Language :: Python :: 3.9
Classifier: Programming Language :: Python :: 3.10
Classifier: Programming Language :: Python :: 3.11
Classifier: License :: OSI Approved :: GNU Lesser General Public License v3 or later (LGPLv3+)
